pyquations/__init__.py
pyquations/algebra/__init__.py
pyquations/algebra/quadratic_formula.py
pyquations/conversions/__init__.py
pyquations/conversions/speed.py
pyquations/geometry/__init__.py
pyquations/geometry/pythagorean_theorem.py
pyquations/physics/__init__.py
pyquations/physics/newtons_second_law.py
pyquations-0.1.0b1.dist-info/licenses/LICENSE
pyquations-0.1.0b1.dist-info/METADATA
pyquations-0.1.0b1.dist-info/WHEEL
pyquations-0.1.0b1.dist-info/top_level.txt
pyquations-0.1.0b1.dist-info/RECORD
