Metadata-Version: 2.4
Name: pyquations
Version: 0.1.0b1
Summary: Simplify utilizing equations in Python.
Author: Mitchell Gottlieb
License-Expression: MIT
Project-URL: Documentation, https://pyquations.com
Project-URL: Source, https://github.com/mitchell-gottlieb/pyquations
Project-URL: Donate, https://github.com/sponsors/mitchell-gottlieb
Classifier: Development Status :: 4 - Beta
Classifier: Intended Audience :: Developers
Classifier: Intended Audience :: Education
Classifier: Intended Audience :: Science/Research
Classifier: Programming Language :: Python :: 3
Classifier: Programming Language :: Python :: 3.9
Classifier: Programming Language :: Python :: 3.10
Classifier: Programming Language :: Python :: 3.11
Classifier: Programming Language :: Python :: 3.12
Classifier: Programming Language :: Python :: 3.13
Classifier: Topic :: Scientific/Engineering :: Mathematics
Requires-Python: >=3.9
License-File: LICENSE
Provides-Extra: dev
Requires-Dist: ruff; extra == "dev"
Provides-Extra: test
Requires-Dist: pytest; extra == "test"
Requires-Dist: pytest-cov; extra == "test"
Provides-Extra: docs
Requires-Dist: sphinx; extra == "docs"
Requires-Dist: pydata-sphinx-theme; extra == "docs"
Dynamic: license-file
